spin/__init__.py
spin/__main__.py
spin/color_format.py
spin/containers.py
spin/sectioned_help.py
spin/cmds/__init__.py
spin/cmds/build.py
spin/cmds/meson.py
spin/cmds/meta.py
spin/cmds/pip.py
spin/cmds/util.py
spin/tests/__init__.py
spin/tests/conftest.py
spin/tests/test_build_cmds.py
spin/tests/test_cli.py
spin/tests/test_editable.py
spin/tests/test_extend_command.py
spin/tests/test_meson.py
spin/tests/test_test.py
spin/tests/test_util.py
spin/tests/testutil.py
spin-0.14.dist-info/licenses/LICENSE
spin-0.14.dist-info/METADATA
spin-0.14.dist-info/WHEEL
spin-0.14.dist-info/entry_points.txt
spin-0.14.dist-info/top_level.txt
spin-0.14.dist-info/RECORD
