Metadata-Version: 2.4
Name: spin
Version: 0.14
Summary: Developer tool for scientific Python libraries
Maintainer-email: Scientific Python <spin@discuss.scientific-python.org>
License: BSD 3-Clause License
Project-URL: homepage, https://github.com/scientific-python/spin
Classifier: Development Status :: 4 - Beta
Classifier: Programming Language :: Python
Classifier: Intended Audience :: Developers
Classifier: Intended Audience :: Science/Research
Classifier: License :: OSI Approved :: BSD License
Classifier: Operating System :: OS Independent
Classifier: Programming Language :: Python :: 3
Classifier: Programming Language :: Python :: 3.9
Classifier: Programming Language :: Python :: 3.10
Classifier: Programming Language :: Python :: 3.11
Classifier: Programming Language :: Python :: 3.12
Classifier: Programming Language :: Python :: 3.13
Classifier: Programming Language :: Python :: 3 :: Only
Requires-Python: >=3.9
License-File: LICENSE
Requires-Dist: click
Requires-Dist: tomli; python_version < "3.11"
Requires-Dist: colorama; platform_system == "Windows"
Requires-Dist: importlib_metadata>=7
Provides-Extra: lint
Requires-Dist: pre-commit==4.2.0; extra == "lint"
Provides-Extra: dev
Requires-Dist: changelist==0.5; extra == "dev"
Dynamic: license-file
